python_typing_update/__init__.py
python_typing_update/__main__.py
python_typing_update/const.py
python_typing_update/main.py
python_typing_update/py.typed
python_typing_update/utils.py
python_typing_update-0.8.1.dist-info/licenses/AUTHORS
python_typing_update-0.8.1.dist-info/licenses/LICENSE
python_typing_update-0.8.1.dist-info/METADATA
python_typing_update-0.8.1.dist-info/WHEEL
python_typing_update-0.8.1.dist-info/entry_points.txt
python_typing_update-0.8.1.dist-info/top_level.txt
python_typing_update-0.8.1.dist-info/RECORD
