Metadata-Version: 2.4
Name: python-typing-update
Version: 0.8.1
Summary: Update Python typing syntax
Author: Marc Mueller
License-Expression: MIT
Project-URL: Source Code, https://github.com/cdce8p/python-typing-update
Keywords: typing,pep585,pep604
Classifier: Development Status :: 4 - Beta
Classifier: Intended Audience :: Developers
Classifier: Programming Language :: Python :: 3.10
Classifier: Programming Language :: Python :: 3.11
Classifier: Programming Language :: Python :: 3.12
Classifier: Programming Language :: Python :: 3.13
Classifier: Programming Language :: Python :: 3.14
Classifier: Topic :: Software Development
Requires-Python: >=3.10
License-File: LICENSE
License-File: AUTHORS
Requires-Dist: aiofiles==25.1.0
Requires-Dist: autoflake==2.3.1
Requires-Dist: isort==7.0.0
Requires-Dist: pyupgrade==3.21.1
Requires-Dist: reorder-python-imports==3.16.0
Provides-Extra: black
Requires-Dist: black==25.11.0; extra == "black"
Provides-Extra: ruff
Requires-Dist: ruff==0.14.4; extra == "ruff"
Dynamic: license-file
